automd/__init__.py
automd/automd.py
automd/decorators.py
automd/encoder.py
automd/http_verbs.py
automd/keys.py
automd/mixedfield.py
automd/registration.py
automd/endpoints/__init__.py
automd/endpoints/openmd_html.py
automd/endpoints/openmd_spec.py
automd/responses/__init__.py
automd/responses/responses.py
automd/templates/__init__.py
automd/templates/openapi.py
AutoMD-1.10.0.dist-info/LICENSE
AutoMD-1.10.0.dist-info/METADATA
AutoMD-1.10.0.dist-info/WHEEL
AutoMD-1.10.0.dist-info/top_level.txt
AutoMD-1.10.0.dist-info/RECORD
