Metadata-Version: 2.1
Name: AutoMD
Version: 1.10.0
Summary: AutoMD is a documentation library for Flask APIs build with FlaskRESTful and Webargs.
Home-page: https://github.com/cliftbar/automd
Author: Cameron Barclift
Author-email: cwbarclift@gmail.com
License: MIT
Platform: any
Classifier: Environment :: Web Environment
Classifier: Intended Audience :: Developers
Classifier: License :: OSI Approved :: MIT License
Classifier: Operating System :: OS Independent
Classifier: Programming Language :: Python
Classifier: Topic :: Internet :: WWW/HTTP :: Dynamic Content
Classifier: Topic :: Software Development :: Libraries :: Python Modules
Requires-Python: >=3.6
Requires-Dist: flask
Requires-Dist: flask-restful
Requires-Dist: webargs
Requires-Dist: apispec
Requires-Dist: pyyaml
Requires-Dist: marshmallow
Requires-Dist: werkzeug
